setup.py
rompar/__init__.py
rompar/cmd.py
rompar/config.py
rompar/data.py
rompar/gui.py
rompar.egg-info/PKG-INFO
rompar.egg-info/SOURCES.txt
rompar.egg-info/dependency_links.txt
rompar.egg-info/top_level.txt