Metadata-Version: 1.1
Name: rompar
Version: 1.0.0
Summary: Mask ROM semi-automatic capture.
Home-page: https://github.com/SiliconAnalysis/rompar
Author: John McMaster
Author-email: JohnDMcMaster@gmail.com
License: GPL
Keywords: mask rom
Platform: UNKNOWN
Classifier: License :: OSI Approved
